bclr/__init__.py
bclr/_version.py
bclr/bclr_helper.py
bclr/bclr_multi.py
bclr/bclr_one.py
bclr/tests/__init__.py
bclr/tests/bclr_multi.npy
bclr/tests/bclr_one.npy
bclr/tests/test_helper.py
bclr/tests/test_multi.py
bclr/tests/test_one.py
bclr-0.3.3.dist-info/licenses/LICENSE
bclr-0.3.3.dist-info/METADATA
bclr-0.3.3.dist-info/WHEEL
bclr-0.3.3.dist-info/top_level.txt
bclr-0.3.3.dist-info/RECORD
