Metadata-Version: 2.4
Name: bclr
Version: 0.3.3
Summary: bclr - Bayesian changepoint detection via Logistic Regression
Author: Andrew M. Thomas and Michael Jauch
Author-email: <me@andrewmthomas.com>
Maintainer: Andrew M. Thomas
Keywords: changepoint,bayesian,logistic regression
Classifier: Operating System :: MacOS
Classifier: Operating System :: Microsoft :: Windows
Classifier: Programming Language :: Python
License-File: LICENSE
Requires-Dist: wheel
Requires-Dist: matplotlib
Requires-Dist: pandas
Requires-Dist: numpy<=1.26.4
Requires-Dist: detectda>=0.5.3
Requires-Dist: joblib
Requires-Dist: tabulate
Requires-Dist: scikit-learn>=1.3.0
Requires-Dist: scipy
Requires-Dist: polyagamma>=1.3.6
Requires-Dist: ruptures>=1.1.8
Dynamic: author
Dynamic: author-email
Dynamic: classifier
Dynamic: description
Dynamic: description-content-type
Dynamic: keywords
Dynamic: license-file
Dynamic: maintainer
Dynamic: requires-dist
Dynamic: summary
